<annotation>
	<folder>train</folder>
	<filename>container_ship-14_jpg.rf.7cadb50496bde5db289d7be4995282ad.jpg</filename>
	<path>/mnt/c/Users/microsoft/Pictures/train/container_ship-14_jpg.rf.7cadb50496bde5db289d7be4995282ad.jpg</path>
	<source>
		<database>Unknown</database>
	</source>
	<size>
		<width>640</width>
		<height>640</height>
		<depth>3</depth>
	</size>
	<segmented>0</segmented>
	<object>
		<name>cargo ship</name>
		<pose>Unspecified</pose>
		<truncated>0</truncated>
		<difficult>0</difficult>
		<bndbox>
			<xmin>72</xmin>
			<ymin>319</ymin>
			<xmax>326</xmax>
			<ymax>453</ymax>
		</bndbox>
	</object>
</annotation>
